pork/__init__.py
pork-0.1.0.dist-info/licenses/LICENSE
pork-0.1.0.dist-info/METADATA
pork-0.1.0.dist-info/WHEEL
pork-0.1.0.dist-info/top_level.txt
pork-0.1.0.dist-info/RECORD
