Metadata-Version: 2.4
Name: pork
Version: 0.1.0
Summary: Add your description here
Requires-Python: >=3.12
License-File: LICENSE
Requires-Dist: numpy>=2.2.5
Requires-Dist: scipy>=1.15.2
Dynamic: license-file
